README.rst
setup.cfg
setup.py
hd_es_tools/__init__.py
hd_es_tools/tools.py
hd_es_tools.egg-info/PKG-INFO
hd_es_tools.egg-info/SOURCES.txt
hd_es_tools.egg-info/dependency_links.txt
hd_es_tools.egg-info/entry_points.txt
hd_es_tools.egg-info/requires.txt
hd_es_tools.egg-info/top_level.txt
hd_es_tools/es_sync/__init__.py
hd_es_tools/es_sync/fav_title_1_pgc/__init__.py
hd_es_tools/es_sync/fav_title_1_pgc/fav_pgc_title.py
hd_es_tools/es_sync/fav_title_2_recipe/__init__.py
hd_es_tools/es_sync/fav_title_2_recipe/fav_recipe_title.py
hd_es_tools/es_sync/fav_title_3_favdir/__init__.py
hd_es_tools/es_sync/fav_title_3_favdir/fav_dir_title.py
hd_es_tools/es_sync/fav_title_sync/__init__.py
hd_es_tools/es_sync/fav_title_sync/task_sync_fav_title.py
hd_es_tools/mongo_connector_doc_managers/__init__.py
hd_es_tools/mongo_connector_doc_managers/config.json
hd_es_tools/mongo_connector_doc_managers/config_fav.json
hd_es_tools/mongo_connector_doc_managers/config_favdir.json
hd_es_tools/mongo_connector_doc_managers/config_msg.json
hd_es_tools/mongo_connector_doc_managers/elastic5_doc_manager.py
hd_es_tools/mongo_connector_doc_managers/formatters_proxy.py
hd_es_tools/mongo_connector_doc_managers/formatters/__init__.py
hd_es_tools/mongo_connector_doc_managers/formatters/fav_formatter.py