Metadata-Version: 1.1
Name: hd-es-tools
Version: 0.2.5
Summary: haodou elasticsearch tools
Home-page: https://github.com/mongodb-labs/elastic2-doc-manager
Author: HaoDou, Inc.
Author-email: huangyue@haodou.com
License: http://www.apache.org/licenses/LICENSE-2.0.html
Keywords: mongo-connector,mongodb,elastic,elasticsearch,haodou
Platform: any
Classifier: Development Status :: 4 - Beta
Classifier: Intended Audience :: Developers
Classifier: License :: OSI Approved :: Apache Software License
Classifier: Programming Language :: Python :: 2.6
Classifier: Programming Language :: Python :: 2.7
Classifier: Programming Language :: Python :: 3.3
Classifier: Programming Language :: Python :: 3.4
Classifier: Programming Language :: Python :: 3.5
Classifier: Topic :: Database
Classifier: Topic :: Software Development :: Libraries :: Python Modules
Classifier: Operating System :: Unix
Classifier: Operating System :: MacOS :: MacOS X
Classifier: Operating System :: Microsoft :: Windows
Classifier: Operating System :: POSIX
